{
  "project_info": {
    "project_number": "136198820190",
    "project_id": "myapp-b8d6d",
    "storage_bucket": "myapp-b8d6d.appspot.com"
  },
  "client": [
    {
      "client_info": {
        "mobilesdk_app_id": "1:136198820190:android:490bad1193dee169f87fcf",
        "android_client_info": {
          "package_name": "com.example.myapp"
        }
      },
      "oauth_client": [],
      "api_key": [
        {
          "current_key": "AIzaSyAAOZz-P1JEJeFw_wmvVXDxbC2IsE08RCY"
        }
      ],
      "services": {
        "appinvite_service": {
          "other_platform_oauth_client": []
        }
      }
    }
  ],
  "configuration_version": "1"
}